setup.py
fiftythree/__init__.py
fiftythree/client.py
fiftythree_client.egg-info/PKG-INFO
fiftythree_client.egg-info/SOURCES.txt
fiftythree_client.egg-info/dependency_links.txt
fiftythree_client.egg-info/requires.txt
fiftythree_client.egg-info/top_level.txt