Metadata-Version: 1.1
Name: fiftythree-client
Version: 1.0.1
Summary: A python client for the 53 API provided by ORGANIZE.org
Home-page: https://github.com/ORGAN-IZE/fiftythree-client
Author: Dana Spiegel
Author-email: dana@organize.org
License: MIT
Platform: UNKNOWN
Classifier: Programming Language :: Python
Classifier: Programming Language :: Python :: 2.7
